CHANGES.rst
MANIFEST.in
README.rst
setup.cfg
setup.py
whenIO/__init__.py
whenIO/tests.py
whenIO.egg-info/PKG-INFO
whenIO.egg-info/SOURCES.txt
whenIO.egg-info/dependency_links.txt
whenIO.egg-info/requires.txt
whenIO.egg-info/top_level.txt
whenIO.egg-info/zip-safe