Metadata-Version: 1.1
Name: whenIO
Version: 1.5
Summary: Methods for formatting and parsing friendly timestamps
Home-page: https://github.com/invisibleroads/whenIO
Author: Roy Hyunjin Han
Author-email: starsareblueandfaraway@gmail.com
License: MIT
Keywords: datetime time
Platform: UNKNOWN
Classifier: Intended Audience :: Developers
Classifier: Programming Language :: Python
Classifier: License :: OSI Approved :: MIT License
